MANIFEST.in
setup.py
mongopony/__init__.py
mongopony/collection.py
mongopony/fields.py
mongopony/local_config.py
mongopony/mapper.py
mongopony/queryplan.py
mongopony.egg-info/PKG-INFO
mongopony.egg-info/SOURCES.txt
mongopony.egg-info/dependency_links.txt
mongopony.egg-info/requires.txt
mongopony.egg-info/top_level.txt
mongopony/tests/__init__.py
mongopony/tests/base.py
mongopony/tests/test_collection.py
mongopony/tests/test_custom_strategy.py
mongopony/tests/test_embedded.py
mongopony/tests/test_persistence.py
mongopony/tests/test_simple_strategy.py