Metadata-Version: 1.1
Name: mongopony
Version: 0.1.2
Summary: A Python document-object mapper for working with MongoDB
Home-page: UNKNOWN
Author: Colin Howe
Author-email: colinthehowe@{nospam}gmail.com
License: MIT
Platform: any
Classifier: Development Status :: 4 - Beta
Classifier: Intended Audience :: Developers
Classifier: License :: OSI Approved :: MIT License
Classifier: Operating System :: OS Independent
Classifier: Programming Language :: Python
Classifier: Topic :: Database
Classifier: Topic :: Software Development :: Libraries :: Python Modules
